<trait name="Scepter2H_E010">
	<dbid>1367</dbid>
	<traittype>Scepter</traittype>
	<rarity>epic</rarity>
	<icon>UserInterface\Icons\Equipment\Generic\Scepters\Scepter_E61_ua</icon>
	<rollovertextid>55673</rollovertextid>
	<displaynameid>55674</displaynameid>
	<offertype>eOfferCivMatching</offertype>
	<visualfactor type="Weapon" factor="61.0000" />
	<sellable>1</sellable>
	<tradeable>1</tradeable>
	<destroyable>1</destroyable>
	<canbestoredingearhall>0</canbestoredingearhall>
	<effects>
		<effect type="Data" bonus="true" amount="1.0055" scaling="0.0020" subtype="WorkRate" visible="true" relativity="Percent" action="Empower" unittype="Dropsite">
			<target type="Player" />
		</effect>
	</effects>
	<levels>
		<level>40</level>
		<level>41</level>
		<level>42</level>
		<level>43</level>
	</levels>
	<craftlevels />
</trait>