<trait name="VanityWeapon1H_016">
	<dbid>2118</dbid>
	<traittype>VanityWeapon</traittype>
	<rarity>common</rarity>
	<icon>/UserInterface/Icons/Equipment/Vanity/116_DragonSlayer_Weapon_ua</icon>
	<rollovertextid>66540</rollovertextid>
	<displaynameid>66541</displaynameid>
	<offertype>eOfferNone</offertype>
	<equipsoundset>UI_Cons_Spc_DragonSlayer</equipsoundset>
	<visualfactor type="VanityWeapon" factor="116.0000" />
	<sellable>1</sellable>
	<tradeable>0</tradeable>
	<destroyable>1</destroyable>
	<canbestoredingearhall>1</canbestoredingearhall>
</trait>