<trait name="Axe2H_U102">
	<dbid>1473</dbid>
	<traittype>GreatAxe</traittype>
	<rarity>uncommon</rarity>
	<icon>UserInterface\Icons\Equipment\Generic\Axes\Axe_U11_ua</icon>
	<rollovertextid>59146</rollovertextid>
	<displaynameid>59147</displaynameid>
	<offertype>eOfferNone</offertype>
	<visualfactor type="Weapon" factor="11.0000" />
	<sellable>1</sellable>
	<tradeable>1</tradeable>
	<destroyable>1</destroyable>
	<canbestoredingearhall>0</canbestoredingearhall>
	<effects>
		<effect type="Data" bonus="true" amount="1.0449" scaling="0.0080" subtype="Damage" visible="true" relativity="Percent" allactions="1">
			<target type="Player" />
		</effect>
		<effect type="Data" bonus="true" amount="1.0049" scaling="0.0008" subtype="HitPercent" visible="true" relativity="Percent" action="MeleeAttack">
			<target type="Player" />
		</effect>
	</effects>
	<levels />
	<craftlevels>
		<level>24</level>
	</craftlevels>
</trait>