<trait name="ArmorBldg_U201">
	<dbid>1901</dbid>
	<traittype>ArmorBuilding</traittype>
	<rarity>uncommon</rarity>
	<icon>UserInterface\Icons\Equipment\Generic\Armor\Bldg\Bldg_U10_ua</icon>
	<rollovertextid>62023</rollovertextid>
	<displaynameid>62024</displaynameid>
	<offertype>eOfferNone</offertype>
	<visualfactor type="Body" factor="10.0000" />
	<sellable>0</sellable>
	<tradeable>0</tradeable>
	<destroyable>1</destroyable>
	<canbestoredingearhall>0</canbestoredingearhall>
	<effects>
		<effect type="Data" bonus="true" amount="1.0500" scaling="0.0090" subtype="Hitpoints" visible="true" relativity="Percent">
			<target type="Player" />
		</effect>
	</effects>
</trait>