<trait name="Gear_Vill_U002">
	<dbid>1068</dbid>
	<traittype>GearVill</traittype>
	<rarity>uncommon</rarity>
	<icon>UserInterface\Icons\Equipment\Generic\Gear\Vill\Hat_U11_ua</icon>
	<rollovertextid>54912</rollovertextid>
	<displaynameid>54913</displaynameid>
	<offertype>eOfferNone</offertype>
	<visualfactor type="Helmet" factor="11.0000" />
	<sellable>1</sellable>
	<tradeable>1</tradeable>
	<destroyable>1</destroyable>
	<canbestoredingearhall>0</canbestoredingearhall>
	<effects>
		<effect type="Data" bonus="true" amount="1.0031" scaling="0.0006" subtype="MaximumVelocity" visible="true" relativity="Percent">
			<target type="Player" />
		</effect>
		<effect type="Data" bonus="true" amount="1.0153" scaling="0.0031" subtype="LOS" visible="true" relativity="Percent">
			<target type="Player" />
		</effect>
	</effects>
	<levels />
	<craftlevels>
		<level>17</level>
	</craftlevels>
</trait>