<trait name="Tool1H_R002">
	<dbid>1015</dbid>
	<traittype>Tools</traittype>
	<rarity>rare</rarity>
	<icon>UserInterface\Icons\Equipment\Generic\Tools\Tool_R30_ua</icon>
	<rollovertextid>54552</rollovertextid>
	<displaynameid>54553</displaynameid>
	<offertype>eOfferCivMatching</offertype>
	<visualfactor type="Weapon" factor="0.0000" />
	<sellable>1</sellable>
	<tradeable>1</tradeable>
	<destroyable>1</destroyable>
	<canbestoredingearhall>0</canbestoredingearhall>
	<effects>
		<effect type="Data" bonus="true" amount="1.0112" scaling="0.0031" subtype="CarryCapacity" visible="false" relativity="Percent" seedoffset="1" resource="Food">
			<target type="Player" />
		</effect>
		<effect type="Data" bonus="true" amount="1.0112" scaling="0.0031" subtype="CarryCapacity" visible="false" relativity="Percent" seedoffset="1" resource="Stone">
			<target type="Player" />
		</effect>
		<effect type="Data" bonus="true" amount="1.0049" scaling="0.0012" subtype="CarryCapacity" visible="false" relativity="Percent" seedoffset="1" resource="Wood">
			<target type="Player" />
		</effect>
		<effect type="Data" bonus="true" amount="1.0112" scaling="0.0031" subtype="CarryCapacity" visible="false" relativity="Percent" seedoffset="1" resource="Gold">
			<target type="Player" />
		</effect>
		<effect type="Data" bonus="true" amount="1.0112" scaling="0.0031" subtype="WorkRate" visible="true" relativity="Percent" seedoffset="1" action="Gather" unittype="AbstractFarm">
			<target type="Player" />
		</effect>
		<effect type="Data" bonus="true" amount="1.0112" scaling="0.0031" subtype="WorkRate" visible="true" relativity="Percent" seedoffset="1" action="Gather" unittype="Huntable">
			<target type="Player" />
		</effect>
		<effect type="Data" bonus="true" amount="1.0049" scaling="0.0012" subtype="WorkRate" visible="true" relativity="Percent" seedoffset="1" action="Gather" unittype="Tree">
			<target type="Player" />
		</effect>
		<effect type="Data" bonus="true" amount="1.0112" scaling="0.0031" subtype="WorkRate" visible="true" relativity="Percent" seedoffset="1" action="Gather" unittype="Gold">
			<target type="Player" />
		</effect>
		<effect type="Data" bonus="true" amount="1.0112" scaling="0.0031" subtype="WorkRate" visible="true" relativity="Percent" seedoffset="1" action="Gather" unittype="AbstractFruit">
			<target type="Player" />
		</effect>
		<effect type="Data" bonus="true" amount="1.0112" scaling="0.0031" subtype="WorkRate" visible="true" relativity="Percent" seedoffset="1" action="FishGather" unittype="AbstractFish">
			<target type="Player" />
		</effect>
		<effect type="Data" bonus="true" amount="1.0112" scaling="0.0031" subtype="WorkRate" visible="true" relativity="Percent" seedoffset="1" action="Gather" unittype="Herdable">
			<target type="Player" />
		</effect>
		<effect type="Data" bonus="true" amount="1.0112" scaling="0.0031" subtype="WorkRate" visible="true" relativity="Percent" seedoffset="1" action="Gather" unittype="Stone">
			<target type="Player" />
		</effect>
	</effects>
	<levels>
		<level>13</level>
		<level>14</level>
		<level>15</level>
		<level>16</level>
		<level>17</level>
	</levels>
	<craftlevels />
</trait>