<trait name="VanityShield1H_007">
	<dbid>1974</dbid>
	<traittype>VanityShield</traittype>
	<rarity>common</rarity>
	<icon>\UserInterface\Icons\Equipment\Vanity\107_Tiki_Shield_ua</icon>
	<rollovertextid>64114</rollovertextid>
	<displaynameid>64115</displaynameid>
	<offertype>eOfferNone</offertype>
	<equipsoundset>UI_Cons_Spc_Tiki</equipsoundset>
	<visualfactor type="VanityShield" factor="107.0000" />
	<sellable>1</sellable>
	<tradeable>0</tradeable>
	<destroyable>1</destroyable>
	<canbestoredingearhall>1</canbestoredingearhall>
</trait>