<trait name="Tool1H_U102">
	<dbid>1603</dbid>
	<traittype>Tools</traittype>
	<rarity>uncommon</rarity>
	<icon>UserInterface\Icons\Equipment\Generic\Tools\Tool_U11_ua</icon>
	<rollovertextid>59406</rollovertextid>
	<displaynameid>59407</displaynameid>
	<offertype>eOfferNone</offertype>
	<visualfactor type="Weapon" factor="0.0000" />
	<sellable>1</sellable>
	<tradeable>1</tradeable>
	<destroyable>1</destroyable>
	<canbestoredingearhall>0</canbestoredingearhall>
	<effects>
		<effect type="Data" bonus="true" amount="1.0125" scaling="0.0022" subtype="CarryCapacity" visible="false" relativity="Percent" seedoffset="1" resource="Food">
			<target type="Player" />
		</effect>
		<effect type="Data" bonus="true" amount="1.0125" scaling="0.0022" subtype="CarryCapacity" visible="false" relativity="Percent" seedoffset="1" resource="Stone">
			<target type="Player" />
		</effect>
		<effect type="Data" bonus="true" amount="1.0125" scaling="0.0022" subtype="CarryCapacity" visible="false" relativity="Percent" seedoffset="1" resource="Wood">
			<target type="Player" />
		</effect>
		<effect type="Data" bonus="true" amount="1.0125" scaling="0.0022" subtype="CarryCapacity" visible="false" relativity="Percent" seedoffset="1" resource="Gold">
			<target type="Player" />
		</effect>
		<effect type="Data" bonus="true" amount="1.0125" scaling="0.0022" subtype="WorkRate" visible="true" relativity="Percent" seedoffset="1" action="Gather" unittype="AbstractFarm">
			<target type="Player" />
		</effect>
		<effect type="Data" bonus="true" amount="1.0125" scaling="0.0022" subtype="WorkRate" visible="true" relativity="Percent" seedoffset="1" action="Gather" unittype="Huntable">
			<target type="Player" />
		</effect>
		<effect type="Data" bonus="true" amount="1.0125" scaling="0.0022" subtype="WorkRate" visible="true" relativity="Percent" seedoffset="1" action="Gather" unittype="Tree">
			<target type="Player" />
		</effect>
		<effect type="Data" bonus="true" amount="1.0125" scaling="0.0022" subtype="WorkRate" visible="true" relativity="Percent" seedoffset="1" action="Gather" unittype="Gold">
			<target type="Player" />
		</effect>
		<effect type="Data" bonus="true" amount="1.0125" scaling="0.0022" subtype="WorkRate" visible="true" relativity="Percent" seedoffset="1" action="FishGather" unittype="AbstractFish">
			<target type="Player" />
		</effect>
		<effect type="Data" bonus="true" amount="1.0125" scaling="0.0022" subtype="WorkRate" visible="true" relativity="Percent" seedoffset="1" action="Gather" unittype="Herdable">
			<target type="Player" />
		</effect>
		<effect type="Data" bonus="true" amount="1.0125" scaling="0.0022" subtype="WorkRate" visible="true" relativity="Percent" seedoffset="1" action="Gather" unittype="Stone">
			<target type="Player" />
		</effect>
		<effect type="Data" bonus="true" amount="1.0125" scaling="0.0022" subtype="WorkRate" visible="true" relativity="Percent" seedoffset="1" action="Gather" unittype="AbstractFruit">
			<target type="Player" />
		</effect>
	</effects>
	<levels>
		<level>12</level>
		<level>13</level>
		<level>14</level>
		<level>15</level>
		<level>16</level>
	</levels>
	<craftlevels />
</trait>